mtg_deckstats/__init__.py
mtg_deckstats/__version__.py
mtg_deckstats/canadian_highlander_step.py
mtg_deckstats/combo_potential_step.py
mtg_deckstats/commander_tier_step.py
mtg_deckstats/create_report_step.py
mtg_deckstats/deck_composition_step.py
mtg_deckstats/graph.py
mtg_deckstats/mana_producers_step.py
mtg_deckstats/mana_value_step.py
mtg_deckstats/parse_deck_step.py
mtg_deckstats/rank.py
mtg_deckstats/rarity_step.py
mtg_deckstats/report.py
mtg_deckstats/salt_step.py
mtg_deckstats/utils.py
mtg_deckstats-0.0.1a8.dist-info/LICENSE
mtg_deckstats-0.0.1a8.dist-info/METADATA
mtg_deckstats-0.0.1a8.dist-info/WHEEL
mtg_deckstats-0.0.1a8.dist-info/entry_points.txt
mtg_deckstats-0.0.1a8.dist-info/RECORD
