Metadata-Version: 2.1
Name: mtg-deckstats
Version: 0.0.1a8
Summary: Magic: the Gathering deckstats
Home-page: https://github.com/lheyberger/mtg-deckstats
License: MIT
Author: Ludovic Heyberger
Author-email: 940408+lheyberger@users.noreply.github.com
Requires-Python: >=3.7,<4.0
Classifier: License :: OSI Approved :: MIT License
Classifier: Programming Language :: Python :: 3
Classifier: Programming Language :: Python :: 3.7
Classifier: Programming Language :: Python :: 3.8
Classifier: Programming Language :: Python :: 3.9
Classifier: Programming Language :: Python :: 3.10
Classifier: Programming Language :: Python :: 3.11
Requires-Dist: beautifulsoup4 (>=4.12.2,<5.0.0)
Requires-Dist: more-itertools (>=9.1.0,<10.0.0)
Requires-Dist: mtg-parser (>=0.0.1a28,<0.0.2)
Requires-Dist: requests (>=2.28.2,<3.0.0)
Project-URL: Documentation, https://github.com/lheyberger/mtg-deckstats
Project-URL: Repository, https://github.com/lheyberger/mtg-deckstats
